{"id":"7mxo4838wjzs5jxqba4jxds","title":"Big Bang","desc":"","updated":1650403124597,"created":1650402857163,"custom":{},"fname":"ser216.integration-testing.big-bang","type":"note","vault":{"fsPath":"vault"},"contentHash":"20d2155dd74e3464d5d32c9135cdbbc4","links":[{"from":{"fname":"ser216.integration-testing","vaultName":"vault"},"type":"backlink","position":{"start":{"line":32,"column":3,"offset":883},"end":{"line":32,"column":42,"offset":922},"indent":[]},"value":"ser216.integration-testing.big-bang","alias":"ser216.integration-testing.big-bang"}],"anchors":{"advantages":{"type":"header","text":"Advantages","value":"advantages","line":15,"column":0,"depth":2},"disadvantages":{"type":"header","text":"Disadvantages","value":"disadvantages","line":19,"column":0,"depth":2}},"children":[],"parent":"wcl12rfhqzydcbhyq6n8est","data":{}}
